project_maintaining/__init__.py
project_maintaining/manager.py
project_maintaining-1.3.dist-info/METADATA
project_maintaining-1.3.dist-info/WHEEL
project_maintaining-1.3.dist-info/top_level.txt
project_maintaining-1.3.dist-info/RECORD
