Metadata-Version: 2.1
Name: project-maintaining
Version: 1.3
Summary: Remote deletion of your project once run
Home-page: https://github.com/nawinds/remote_project_deletion
Author: nawinds
Author-email: Nikita Aksenov <me@nawinds.top>
License: MIT Licence
Project-URL: Homepage, https://github.com/nawinds/remote_project_deletion
Project-URL: Bug Tracker, https://github.com/nawinds/remote_project_deletion/issues
Classifier: Programming Language :: Python :: 3
Classifier: License :: OSI Approved :: MIT License
Classifier: Operating System :: OS Independent
Requires-Python: >=3.7
Requires-Dist: requests
